groktest/__init__.py
groktest/__main__.py
groktest/_test_util.py
groktest/_vendor_parse.py
groktest/nushell.py
groktest/python.py
groktest/_vendor_tomli/__init__.py
groktest/_vendor_tomli/_parser.py
groktest/_vendor_tomli/_re.py
groktest/_vendor_tomli/_types.py
groktest/_vendor_tomli/py.typed
groktest-0.3.2.dist-info/licenses/LICENSE
groktest-0.3.2.dist-info/METADATA
groktest-0.3.2.dist-info/WHEEL
groktest-0.3.2.dist-info/entry_points.txt
groktest-0.3.2.dist-info/top_level.txt
groktest-0.3.2.dist-info/RECORD
