Metadata-Version: 2.4
Name: groktest
Version: 0.3.2
Summary: Literate testing framework based on Python doctest
Author-email: Garrett Smith <garrett@placeon.earth>
Project-URL: Homepage, https://github.com/gar1t/groktest
Project-URL: Bug Tracker, https://github.com/gar1t/groktest/issues
Classifier: Programming Language :: Python :: 3
Classifier: License :: OSI Approved :: Apache Software License
Classifier: Operating System :: OS Independent
Requires-Python: >=3.8
License-File: LICENSE
Requires-Dist: pyyaml
Provides-Extra: dev
Requires-Dist: black; extra == "dev"
Requires-Dist: build; extra == "dev"
Requires-Dist: twine; extra == "dev"
Dynamic: license-file
